sine_properties_estimation/__init__.py
sine_properties_estimation/estimation.py
sine_properties_estimation-0.1.1.dist-info/LICENSE
sine_properties_estimation-0.1.1.dist-info/METADATA
sine_properties_estimation-0.1.1.dist-info/WHEEL
sine_properties_estimation-0.1.1.dist-info/top_level.txt
sine_properties_estimation-0.1.1.dist-info/RECORD
