Metadata-Version: 2.1
Name: sine-properties-estimation
Version: 0.1.1
Summary: estimate sine frequency, amp, phase and offset from 1D raw data
Home-page: https://github.com/lisrael1/sine_properties_estimation
Author: Lior Israeli
Author-email: israelilior@gmail.com
License: UNKNOWN
Project-URL: Bug Tracker, https://github.com/lisrael1/sine_properties_estimation/issues
Platform: UNKNOWN
Classifier: Programming Language :: Python :: 3
Classifier: License :: OSI Approved :: MIT License
Classifier: Operating System :: OS Independent
Requires-Python: >=3.6
License-File: LICENSE
Requires-Dist: numpy
Requires-Dist: pandas
Requires-Dist: scipy
Requires-Dist: dict-aligned-print
